netwalk/__init__.py
netwalk/device.py
netwalk/fabric.py
netwalk/interface.py
netwalk/libs.py
netwalk/textfsm_templates/show_cdp_neigh_detail.textfsm
netwalk/textfsm_templates/show_interface.textfsm
netwalk/textfsm_templates/show_inventory.textfsm
netwalk/textfsm_templates/show_lldp_neigh_detail.textfsm
tests/__init__.py
tests/test_fabric.py
tests/test_interface.py
tests/test_ios11.py
tests/test_switch.py
netwalk-1.6.1.dist-info/LICENSE.txt
netwalk-1.6.1.dist-info/METADATA
netwalk-1.6.1.dist-info/NOTICE
netwalk-1.6.1.dist-info/WHEEL
netwalk-1.6.1.dist-info/top_level.txt
netwalk-1.6.1.dist-info/RECORD
