Metadata-Version: 2.1
Name: netwalk
Version: 1.6.1
Summary: Network discovery and analysis tool
Home-page: https://github.com/icovada/netwalk
Author: =?utf-8?q?Federico_Tabb=C3=B2_=28Europe=29?=
Author-email: federico.tabbo@global.ntt
Project-URL: Bug Tracker, https://github.com/icovada/netwalk/issues
Classifier: Programming Language :: Python :: 3
Classifier: Operating System :: OS Independent
Requires-Python: >=3.10
License-File: LICENSE.txt
License-File: NOTICE
Requires-Dist: ciscoconfparse (==1.6.50)
Requires-Dist: napalm (==4.0.0)
